odoo/addons/purchase_variant_configurator/README.rst
odoo/addons/purchase_variant_configurator/__init__.py
odoo/addons/purchase_variant_configurator/__manifest__.py
odoo/addons/purchase_variant_configurator/hooks.py
odoo/addons/purchase_variant_configurator/i18n/es.po
odoo/addons/purchase_variant_configurator/i18n/es_AR.po
odoo/addons/purchase_variant_configurator/i18n/fr.po
odoo/addons/purchase_variant_configurator/i18n/hr.po
odoo/addons/purchase_variant_configurator/i18n/it.po
odoo/addons/purchase_variant_configurator/i18n/pt_BR.po
odoo/addons/purchase_variant_configurator/i18n/purchase_variant_configurator.pot
odoo/addons/purchase_variant_configurator/i18n/ro.po
odoo/addons/purchase_variant_configurator/i18n/sl.po
odoo/addons/purchase_variant_configurator/models/__init__.py
odoo/addons/purchase_variant_configurator/models/purchase_order_line.py
odoo/addons/purchase_variant_configurator/readme/CONTRIBUTORS.rst
odoo/addons/purchase_variant_configurator/readme/DESCRIPTION.rst
odoo/addons/purchase_variant_configurator/static/description/icon.png
odoo/addons/purchase_variant_configurator/static/description/index.html
odoo/addons/purchase_variant_configurator/tests/__init__.py
odoo/addons/purchase_variant_configurator/tests/test_purchase_order.py
odoo/addons/purchase_variant_configurator/views/inherited_purchase_order_views.xml
odoo13_addon_purchase_variant_configurator-13.0.1.0.1.dev6.dist-info/METADATA
odoo13_addon_purchase_variant_configurator-13.0.1.0.1.dev6.dist-info/WHEEL
odoo13_addon_purchase_variant_configurator-13.0.1.0.1.dev6.dist-info/top_level.txt
odoo13_addon_purchase_variant_configurator-13.0.1.0.1.dev6.dist-info/RECORD
